{"physics.ed-ph":9,"hep-lat":378,"cs.SE":17,"math.DS":97,"astro-ph.EP":47,"physics.comp-ph":33,"cond-mat.mes-hall":222,"cs.IR":9,"astro-ph.GA":74,"math.OA":36,"cs.NA":9,"nlin.CG":9,"cond-mat.other":64,"cond-mat.dis-nn":53,"cs.LG":16,"cs.SC":6,"math.GT":57,"math.CV":39,"physics.optics":73,"math.OC":51,"math.IT":81,"q-bio.OT":3,"cs.DL":2,"math.RT":110,"cs.GT":17,"stat.OT":1,"alg-geom":5,"cs.CG":9,"math.AT":28,"cs.AR":3,"q-fin.PR":14,"acc-phys":1,"cond-mat.mtrl-sci":196,"cond-mat.str-el":159,"cs.CE":18,"cond-mat.soft":77,"math.MG":26,"physics.hist-ph":8,"cs.DS":48,"math.SP":28,"cond-mat.stat-mech":149,"math.ST":68,"quant-ph":352,"physics.med-ph":6,"physics.data-an":27,"nlin.AO":24,"stat.TH":68,"physics.space-ph":12,"q-alg":7,"math.NA":44,"cs.RO":6,"q-fin.ST":12,"cond-mat":33,"astro-ph.CO":258,"cs.MM":3,"stat.ME":24,"cs.MA":6,"math.AC":43,"physics.chem-ph":27,"gr-qc":1007,"physics.ao-ph":13,"physics.atm-clus":4,"q-bio.MN":9,"math.KT":16,"cs.CL":7,"math.HO":8,"cs.LO":38,"physics.plasm-ph":34,"math.DG":112,"q-fin.RM":8,"cs.GR":4,"cond-mat.quant-gas":63,"cs.AI":29,"nlin.SI":36,"cs.PF":6,"cs.CY":4,"cs.OS":1,"math.CA":69,"hep-th":1572,"cs.MS":4,"physics.pop-ph":11,"nlin.CD":38,"cs.FL":15,"q-bio.QM":23,"q-bio.SC":1,"q-bio.PE":32,"astro-ph.SR":153,"math.GR":56,"stat.ML":31,"q-fin.TR":4,"q-fin.CP":11,"q-bio.TO":2,"math.QA":60,"nlin.PS":24,"cs.IT":81,"math.LO":40,"cs.CV":15,"cs.CC":29,"math.SG":18,"cs.DB":4,"astro-ph.HE":127,"math.PR":193,"math.CO":182,"funct-an":2,"math.GM":12,"astro-ph.IM":59,"cs.DM":38,"q-bio.NC":19,"cs.NE":8,"nucl-ex":106,"cs.DC":22,"cs.PL":11,"supr-con":1,"math.AG":159,"cs.NI":54,"cs.SY":4,"astro-ph":1037,"physics.geo-ph":32,"q-fin.GN":13,"q-bio.BM":8,"cs.OH":13,"physics.atom-ph":46,"q-bio.CB":7,"physics.flu-dyn":38,"math.RA":57,"math.FA":70,"stat.AP":66,"physics.bio-ph":36,"hep-ex":267,"hep-ph":1844,"physics.soc-ph":48,"cond-mat.supr-con":116,"physics.acc-ph":27,"nucl-th":310,"stat.CO":20,"cs.SI":22,"math.AP":140,"cs.CR":35,"math.CT":18,"math.GN":39,"math.MP":588,"cs.HC":9,"math.NT":90,"physics.ins-det":44,"q-bio.GN":2,"q-fin.PM":8,"physics.gen-ph":55,"physics.class-ph":25}