{"hep-ex":5,"physics.acc-ph":1,"cond-mat.str-el":7,"physics.gen-ph":1,"cond-mat.other":3,"cs.SI":1,"cs.IT":1,"nucl-th":8,"physics.hist-ph":1,"astro-ph":14,"quant-ph":20,"astro-ph.HE":23,"physics.chem-ph":1,"physics.bio-ph":2,"q-bio.TO":1,"math.MP":22,"math.DG":4,"math.RA":1,"physics.flu-dyn":2,"hep-th":29,"physics.data-an":2,"gr-qc":15,"physics.soc-ph":3,"astro-ph.GA":29,"stat.AP":1,"math.NA":2,"astro-ph.CO":27,"q-bio.PE":1,"hep-lat":2,"cs.LG":2,"math.CO":2,"physics.atom-ph":3,"physics.geo-ph":1,"q-bio.CB":1,"cond-mat.mes-hall":11,"astro-ph.SR":30,"math.IT":1,"math.CA":1,"math.DS":2,"cond-mat.stat-mech":11,"physics.class-ph":2,"math.PR":4,"nlin.SI":2,"cond-mat.quant-gas":3,"math.AG":1,"physics.comp-ph":2,"stat.ML":1,"physics.ins-det":1,"cond-mat.soft":6,"cond-mat.mtrl-sci":9,"cond-mat.dis-nn":3,"cs.CR":1,"q-bio.BM":2,"astro-ph.EP":6,"hep-ph":26,"physics.optics":6,"nlin.PS":2,"cs.NA":2,"cond-mat":2,"physics.space-ph":2,"physics.plasm-ph":4,"astro-ph.IM":4,"math.QA":1,"cond-mat.supr-con":8,"nlin.CD":1}