{"math.ST":189,"nucl-ex":119,"physics.ao-ph":78,"q-fin.RM":22,"q-fin.TR":15,"cs.DS":224,"q-bio.QM":113,"math.PR":379,"cs.LG":3014,"cs.HC":308,"physics.geo-ph":48,"hep-ex":281,"q-fin.ST":29,"stat.AP":205,"math.RT":165,"cs.PL":91,"q-fin.MF":31,"physics.data-an":71,"cs.CC":77,"cond-mat.other":49,"nucl-th":220,"math.CA":108,"physics.ins-det":141,"q-bio.PE":75,"math.LO":107,"cs.CV":2112,"cs.MS":20,"math.GR":130,"q-fin.EC":66,"nlin.CD":66,"eess.IV":413,"physics.ed-ph":26,"math.AC":66,"astro-ph.EP":244,"cs.SC":16,"hep-th":686,"astro-ph.SR":358,"cs.CY":272,"math.OC":507,"cs.OS":11,"cs.SY":457,"physics.acc-ph":49,"cond-mat.quant-gas":133,"cs.CE":114,"stat.CO":69,"astro-ph.CO":371,"cs.GL":1,"physics.atom-ph":136,"cs.MA":104,"cs.AI":2001,"eess.SY":456,"math.QA":70,"cond-mat.dis-nn":114,"cs.ET":83,"nlin.AO":42,"q-bio.BM":48,"astro-ph.IM":290,"physics.hist-ph":32,"quant-ph":1153,"stat.ME":332,"cs.DB":81,"math.OA":57,"cond-mat.mtrl-sci":660,"math.NT":264,"physics.plasm-ph":124,"math.AP":463,"cond-mat.stat-mech":317,"eess.SP":396,"q-bio.GN":25,"physics.flu-dyn":286,"cs.FL":44,"math.GM":31,"cs.NA":347,"math.CO":490,"q-fin.PR":10,"cs.AR":85,"cs.DC":234,"gr-qc":597,"cs.CG":50,"nlin.SI":36,"cs.NE":157,"hep-ph":648,"cs.GR":103,"econ.GN":66,"math.NA":348,"physics.soc-ph":153,"math.CV":102,"cond-mat.mes-hall":500,"q-bio.TO":21,"cs.RO":510,"q-fin.CP":19,"eess.AS":186,"stat.TH":189,"physics.class-ph":36,"physics.comp-ph":178,"math.KT":37,"cs.CL":1257,"math.DG":218,"q-bio.NC":87,"cs.PF":36,"physics.atm-clus":9,"math.HO":25,"q-bio.OT":9,"physics.med-ph":79,"cs.DL":38,"astro-ph.HE":507,"math.GT":149,"math.SP":52,"cs.SI":154,"math.AG":291,"math.CT":84,"physics.space-ph":47,"astro-ph.GA":511,"cs.GT":103,"cond-mat.str-el":402,"cs.CR":415,"physics.optics":366,"physics.app-ph":246,"cs.MM":106,"cs.LO":125,"physics.gen-ph":17,"q-fin.PM":19,"nlin.CG":4,"math.AT":137,"q-bio.CB":8,"cs.DM":85,"cond-mat.supr-con":188,"math.MP":926,"math.SG":48,"math.GN":31,"cs.SD":146,"econ.TH":39,"stat.OT":13,"q-bio.SC":4,"physics.bio-ph":92,"physics.pop-ph":9,"cs.IR":207,"math.MG":77,"math.FA":154,"q-fin.GN":20,"stat.ML":567,"econ.EM":57,"math.RA":109,"physics.chem-ph":205,"cond-mat.soft":204,"nlin.PS":34,"hep-lat":110,"q-bio.MN":14,"cs.OH":5,"cs.IT":291,"cs.SE":219,"cs.NI":187,"math.IT":291,"math.DS":299}